ShiyanlouCJiaochengHeji20160904Fix1/README.md
ShiyanlouCJiaochengHeji20160904Fix1/__init__.py
ShiyanlouCJiaochengHeji20160904Fix1/__main__.py
ShiyanlouCJiaochengHeji20160904Fix1/file.epub
ShiyanlouCJiaochengHeji20160904Fix1/index.html
ShiyanlouCJiaochengHeji20160904Fix1/css/__init__.py
ShiyanlouCJiaochengHeji20160904Fix1/css/annotations.css
ShiyanlouCJiaochengHeji20160904Fix1/css/main.css
ShiyanlouCJiaochengHeji20160904Fix1/css/normalize.css
ShiyanlouCJiaochengHeji20160904Fix1/css/popup.css
ShiyanlouCJiaochengHeji20160904Fix1/font/__init__.py
ShiyanlouCJiaochengHeji20160904Fix1/font/fontello.eot
ShiyanlouCJiaochengHeji20160904Fix1/font/fontello.svg
ShiyanlouCJiaochengHeji20160904Fix1/font/fontello.ttf
ShiyanlouCJiaochengHeji20160904Fix1/font/fontello.woff
ShiyanlouCJiaochengHeji20160904Fix1/img/__init__.py
ShiyanlouCJiaochengHeji20160904Fix1/img/annotator-glyph-sprite.png
ShiyanlouCJiaochengHeji20160904Fix1/img/annotator-icon-sprite.png
ShiyanlouCJiaochengHeji20160904Fix1/img/apple-touch-icon.png
ShiyanlouCJiaochengHeji20160904Fix1/img/cancelfullscreen.png
ShiyanlouCJiaochengHeji20160904Fix1/img/close.png
ShiyanlouCJiaochengHeji20160904Fix1/img/fullscreen.png
ShiyanlouCJiaochengHeji20160904Fix1/img/loader.gif
ShiyanlouCJiaochengHeji20160904Fix1/img/menu-icon.png
ShiyanlouCJiaochengHeji20160904Fix1/img/save.png
ShiyanlouCJiaochengHeji20160904Fix1/img/saved.png
ShiyanlouCJiaochengHeji20160904Fix1/img/settings-s.png
ShiyanlouCJiaochengHeji20160904Fix1/img/settings.png
ShiyanlouCJiaochengHeji20160904Fix1/img/star.png
ShiyanlouCJiaochengHeji20160904Fix1/js/__init__.py
ShiyanlouCJiaochengHeji20160904Fix1/js/epub.js
ShiyanlouCJiaochengHeji20160904Fix1/js/epub.min.js
ShiyanlouCJiaochengHeji20160904Fix1/js/epub.min.map
ShiyanlouCJiaochengHeji20160904Fix1/js/hooks.min.js
ShiyanlouCJiaochengHeji20160904Fix1/js/hooks.min.map
ShiyanlouCJiaochengHeji20160904Fix1/js/reader.js
ShiyanlouCJiaochengHeji20160904Fix1/js/reader.js.map
ShiyanlouCJiaochengHeji20160904Fix1/js/reader.min.js
shiyanlou_c_jiaocheng_heji_20160904_fix1-2024.3.1.0.dist-info/METADATA
shiyanlou_c_jiaocheng_heji_20160904_fix1-2024.3.1.0.dist-info/WHEEL
shiyanlou_c_jiaocheng_heji_20160904_fix1-2024.3.1.0.dist-info/entry_points.txt
shiyanlou_c_jiaocheng_heji_20160904_fix1-2024.3.1.0.dist-info/top_level.txt
shiyanlou_c_jiaocheng_heji_20160904_fix1-2024.3.1.0.dist-info/RECORD
